pythocrypt/__init__.py
pythocrypt/caesar.py
pythocrypt/rail_fence.py
pythocrypt/trevanion.py
pythocrypt/common/__init__.py
pythocrypt/common/english_words.txt
pythocrypt/common/utils.py
pythocrypt-0.4.dist-info/LICENSE
pythocrypt-0.4.dist-info/METADATA
pythocrypt-0.4.dist-info/WHEEL
pythocrypt-0.4.dist-info/top_level.txt
pythocrypt-0.4.dist-info/RECORD
