Metadata-Version: 2.1
Name: pythocrypt
Version: 0.4
Summary: Several ciphers for python
Home-page: https://github.com/hugoespinelli/pythocrypt
Author: Hugo Espinelli
Author-email: hugoespinelli@gmail.com
License: MIT
Platform: UNKNOWN
Classifier: Programming Language :: Python :: 3
Classifier: License :: OSI Approved :: MIT License
Classifier: Operating System :: OS Independent
Classifier: Development Status :: 2 - Pre-Alpha
Classifier: Topic :: Security :: Cryptography
Requires-Python: >=3.6
